aimet_ml/__init__.py
aimet_ml/features/__init__.py
aimet_ml/features/audio/__init__.py
aimet_ml/features/facial/__init__.py
aimet_ml/features/textual/__init__.py
aimet_ml/features/textual/transformers.py
aimet_ml/metrics/__init__.py
aimet_ml/metrics/plots.py
aimet_ml/metrics/reports.py
aimet_ml/model_selection/__init__.py
aimet_ml/model_selection/splits.py
aimet_ml/processing/__init__.py
aimet_ml/processing/audio.py
aimet_ml/processing/text.py
aimet_ml/processing/video.py
aimet_ml/resources/audios/sample.wav
aimet_ml/resources/fonts/thsarabunnew-webfont.ttf
aimet_ml/resources/videos/sample.mp4
aimet_ml/utils/__init__.py
aimet_ml/utils/aws.py
aimet_ml/utils/git.py
aimet_ml/utils/hamd_7.py
aimet_ml/utils/io_utils.py
aimet_ml/utils/plots.py
aimet_ml/utils/wandb_utils.py
aimet_ml-1.0.1.dist-info/LICENSE
aimet_ml-1.0.1.dist-info/METADATA
aimet_ml-1.0.1.dist-info/WHEEL
aimet_ml-1.0.1.dist-info/RECORD
